qmap/__version__.py
qmap_benchmark-0.0.0.dist-info/METADATA
qmap_benchmark-0.0.0.dist-info/WHEEL
qmap_benchmark-0.0.0.dist-info/RECORD
