Metadata-Version: 2.4
Name: QMAP-Benchmark
Version: 0.0.0
Summary: Benchmark for AMP MIC regression with a Toolkit to split peptide sequences datasets into independent sets based on pseudo identity
Keywords: clustering,database,deep learning,machine learning,protein,qmap,sequence
Requires-Python: >=3.9
Requires-Dist: antho-utils>=0.1.0
Requires-Dist: huggingface-hub>=0.34.3
Requires-Dist: igraph>=0.11.9
Requires-Dist: leidenalg>=0.10.2
Requires-Dist: numpy>=1.22
Requires-Dist: pandas>=1.4
Requires-Dist: safetensors>=0.5.3
Requires-Dist: scipy>=1.10.1
Requires-Dist: torch>=2.2
